grzymala/__init__.py
grzymala/hello.py
grzymala/loader.py
grzymala/utils.py
grzymala-1.0.0.dist-info/LICENSE
grzymala-1.0.0.dist-info/METADATA
grzymala-1.0.0.dist-info/WHEEL
grzymala-1.0.0.dist-info/top_level.txt
grzymala-1.0.0.dist-info/RECORD
