Metadata-Version: 2.1
Name: grzymala
Version: 1.0.0
Summary: Package for solving geodesy problems
Home-page: UNKNOWN
Author: geodeta
Author-email: jte22466@nezid.com
License: UNKNOWN
Keywords: python,geodesy,forward problem,inverse problem,coordinates,hirvonen
Platform: UNKNOWN
Classifier: Development Status :: 1 - Planning
Classifier: Programming Language :: Python :: 3
Classifier: Operating System :: OS Independent
Classifier: License :: OSI Approved :: MIT License
License-File: LICENSE
Requires-Dist: numpy
Requires-Dist: matplotlib
